azure_tools/__init__.py
azure_tools/aml.py
azure_tools/main.py
azure_tools/progress.py
azure_tools-0.1.3.dist-info/METADATA
azure_tools-0.1.3.dist-info/WHEEL
azure_tools-0.1.3.dist-info/entry_points.txt
azure_tools-0.1.3.dist-info/RECORD
