Metadata-Version: 2.3
Name: azure-tools
Version: 0.1.3
Summary: Convenience CLI tools to work with Microsoft Azure.
Project-URL: Homepage, https://github.com/fepegar/azure-tools
Project-URL: Source, https://github.com/fepegar/azure-tools
Author-email: Fernando Pérez-García <fepegar@gmail.com>
Requires-Python: >=3.9
Requires-Dist: azureml-core
Requires-Dist: humanize
Requires-Dist: loguru
Requires-Dist: setuptools
Requires-Dist: typer
